shipcal/__init__.py
shipcal/__main__.py
shipcal/elements.py
shipcal/energy_consumer.py
shipcal/shipcal.py
shipcal/collectors/__init__.py
shipcal/collectors/collector.py
shipcal/legacy/SHIPcal.py
shipcal/legacy/__init__.py
shipcal/legacy/sliced_SHIPcal.py
shipcal/legacy/Finance_modules/FinanceModels.py
shipcal/legacy/Finance_modules/__init__.py
shipcal/legacy/General_modules/Consumo_random_year.py
shipcal/legacy/General_modules/__init__.py
shipcal/legacy/General_modules/demandCreator_v1.py
shipcal/legacy/General_modules/fromDjangotoSHIPcal.py
shipcal/legacy/General_modules/func_General.py
shipcal/legacy/General_modules/iapws95.py
shipcal/legacy/General_modules/iapws97.py
shipcal/legacy/General_modules/meteo_average.py
shipcal/legacy/Integration_modules/__init__.py
shipcal/legacy/Integration_modules/integrations.py
shipcal/legacy/Plot_modules/__init__.py
shipcal/legacy/Plot_modules/plottingSHIPcal.py
shipcal/legacy/Solar_modules/EQSolares.py
shipcal/legacy/Solar_modules/IAM_data.py
shipcal/legacy/Solar_modules/Meteo_data.py
shipcal/legacy/Solar_modules/__init__.py
shipcal/legacy/Solar_modules/char_day.py
shipcal/legacy/Solar_modules/iteration_process.py
shipcal/legacy/Solar_modules/pos_sun_year.py
shipcal/weather/__init__.py
shipcal/weather/weather.py
shipcal/weather/data/Sevilla.csv
shipcal-2.0.0.dist-info/LICENSE
shipcal-2.0.0.dist-info/METADATA
shipcal-2.0.0.dist-info/WHEEL
shipcal-2.0.0.dist-info/top_level.txt
shipcal-2.0.0.dist-info/RECORD
