Metadata-Version: 2.1
Name: shipcal
Version: 2.0.0
Summary: Solar Heat for Industrial Processes calculator
Home-page: https://github.com/mfrasquet/SHIPcal
Download-URL: https://github.com/mfrasquet/SHIPcal/releases
Author: Miguel Frasquet Herraiz
Maintainer: Juan Antonio Aramburo Pasapera
Maintainer-email: ja.arpa97@gmail.com
License: MIT
Project-URL: Bug Tracker, https://github.com/mfrasquet/SHIPcal/issues
Project-URL: Documentation, https://github.com/mfrasquet/SHIPcal/wiki
Project-URL: Source Code, https://github.com/mfrasquet/SHIPcal
Keywords: solar heat industrial processes calculator simulator
Platform: any
Classifier: Development Status :: 2 - Pre-Alpha
Classifier: Environment :: Console
Classifier: Intended Audience :: Science/Research
Classifier: Intended Audience :: Manufacturing
Classifier: Intended Audience :: Developers
Classifier: License :: OSI Approved :: MIT License
Classifier: Natural Language :: English
Classifier: Operating System :: OS Independent
Classifier: Programming Language :: Python :: 3 :: Only
Classifier: Topic :: Office/Business :: Financial :: Investment
Classifier: Topic :: Scientific/Engineering
Requires-Python: >=3.6
License-File: LICENSE
Requires-Dist: numpy (>=1.16)
Requires-Dist: pandas (>=0.22)
Requires-Dist: pvlib (>=0.9)
Requires-Dist: iapws (>=1.5)
